gitghost/__init__.py
gitghost/cli.py
gitghost-1.0.4.dist-info/METADATA
gitghost-1.0.4.dist-info/WHEEL
gitghost-1.0.4.dist-info/entry_points.txt
gitghost-1.0.4.dist-info/top_level.txt
gitghost-1.0.4.dist-info/RECORD
