Metadata-Version: 2.4
Name: gitghost
Version: 1.0.4
Summary: Private version control for your Git ignored files.
Author: Decoding Chris
License-Expression: MIT
Project-URL: Homepage, https://github.com/decodingchris/GitGhost
Project-URL: Issues, https://github.com/decodingchris/gitghost/issues
Classifier: Programming Language :: Python :: 3
Classifier: Programming Language :: Python :: 3.10
Classifier: Programming Language :: Python :: 3.11
Classifier: Programming Language :: Python :: 3.12
Classifier: Programming Language :: Python :: 3.13
Classifier: Operating System :: POSIX :: Linux
Classifier: Intended Audience :: Developers
Classifier: Topic :: Software Development :: Version Control
Requires-Python: >=3.10
Requires-Dist: click<9.0,>=8.0
Requires-Dist: gitpython<4.0,>=3.1
